e_ok_api/__init__.py
e_ok_api/e_ok_api.py
e_ok_api-0.1.2.dist-info/LICENSE
e_ok_api-0.1.2.dist-info/METADATA
e_ok_api-0.1.2.dist-info/WHEEL
e_ok_api-0.1.2.dist-info/top_level.txt
e_ok_api-0.1.2.dist-info/RECORD
